ad_material_mcp/__init__.py
ad_material_mcp-0.1.4.dist-info/METADATA
ad_material_mcp-0.1.4.dist-info/WHEEL
ad_material_mcp-0.1.4.dist-info/entry_points.txt
ad_material_mcp-0.1.4.dist-info/RECORD
