Metadata-Version: 2.4
Name: ad-material-mcp
Version: 0.1.4
Summary: Add your description here
Author: 刘松奇
Requires-Python: >=3.11
Requires-Dist: mcp[cli]>=1.10.1
